updog2/__init__.py
updog2/__main__.py
updog2/static/css/bootstrap.min.css
updog2/static/css/font.scss
updog2/static/css/images.min.css
updog2/static/css/shared.min.css
updog2/static/css/style.min.css
updog2/static/css/style.scss
updog2/static/fonts/poppins/poppins-v5-latin-300.eot
updog2/static/fonts/poppins/poppins-v5-latin-300.svg
updog2/static/fonts/poppins/poppins-v5-latin-300.ttf
updog2/static/fonts/poppins/poppins-v5-latin-300.woff
updog2/static/fonts/poppins/poppins-v5-latin-300.woff2
updog2/static/fonts/poppins/poppins-v5-latin-600.eot
updog2/static/fonts/poppins/poppins-v5-latin-600.svg
updog2/static/fonts/poppins/poppins-v5-latin-600.ttf
updog2/static/fonts/poppins/poppins-v5-latin-600.woff
updog2/static/fonts/poppins/poppins-v5-latin-600.woff2
updog2/static/images/example.png
updog2/static/images/example2.png
updog2/static/images/favicon.ico
updog2/static/images/updog.png
updog2/static/js/images.min.js
updog2/static/js/jquery-3.4.1.min.js
updog2/static/js/lazysizes.min.js
updog2/static/js/main.min.js
updog2/static/vendor/datatable/datatables.min.css
updog2/static/vendor/datatable/datatables.min.js
updog2/static/vendor/datatable/file-size.js
updog2/static/vendor/datatable/DataTables-1.10.18/images/sort_asc.png
updog2/static/vendor/datatable/DataTables-1.10.18/images/sort_asc_disabled.png
updog2/static/vendor/datatable/DataTables-1.10.18/images/sort_both.png
updog2/static/vendor/datatable/DataTables-1.10.18/images/sort_desc.png
updog2/static/vendor/datatable/DataTables-1.10.18/images/sort_desc_disabled.png
updog2/static/vendor/fontawesome-5.1/LICENSE.txt
updog2/static/vendor/fontawesome-5.1/css/all.min.css
updog2/static/vendor/fontawesome-5.1/webfonts/fa-brands-400.eot
updog2/static/vendor/fontawesome-5.1/webfonts/fa-brands-400.svg
updog2/static/vendor/fontawesome-5.1/webfonts/fa-brands-400.ttf
updog2/static/vendor/fontawesome-5.1/webfonts/fa-brands-400.woff
updog2/static/vendor/fontawesome-5.1/webfonts/fa-brands-400.woff2
updog2-2.2.0.dist-info/LICENSE
updog2-2.2.0.dist-info/METADATA
updog2-2.2.0.dist-info/WHEEL
updog2-2.2.0.dist-info/entry_points.txt
updog2-2.2.0.dist-info/top_level.txt
updog2-2.2.0.dist-info/RECORD
