Metadata-Version: 2.1
Name: updog2
Version: 2.2.0
Summary: Updog is a replacement for Python's SimpleHTTPServer. It allows uploading and downloading via HTTP/S, can set ad hoc SSL certificates and use http basic auth. The last version allows to generate a QR code to share the link and also allows to display just image files in a more friendly way.
Home-page: https://github.com/OBoladeras/updog2
Download-URL: https://github.com/OBoladeras/updog2/archive/updog-2.2.0.tar.gz
Author: OBoladeras
Author-email: oriolboladeras@gmail.com
License: MIT
Keywords: HTTP server SimpleHTTPServer directory
Classifier: Development Status :: 5 - Production/Stable
Classifier: Environment :: Console
Classifier: Environment :: Web Environment
Classifier: Framework :: Flask
Classifier: Intended Audience :: Developers
Classifier: Intended Audience :: System Administrators
Classifier: License :: OSI Approved :: MIT License
Classifier: Natural Language :: English
Classifier: Operating System :: MacOS
Classifier: Operating System :: Microsoft :: Windows
Classifier: Operating System :: POSIX
Classifier: Programming Language :: Python :: 3
Classifier: Programming Language :: Python :: 3.4
Classifier: Programming Language :: Python :: 3.5
Classifier: Programming Language :: Python :: 3.6
Classifier: Programming Language :: Python :: 3.7
Classifier: Programming Language :: Python :: 3.8
Classifier: Programming Language :: Python :: 3.9
Classifier: Programming Language :: Python :: 3.10
Classifier: Topic :: Communications :: File Sharing
Classifier: Topic :: Internet :: WWW/HTTP
Classifier: Topic :: Internet :: WWW/HTTP :: WSGI
Classifier: Topic :: Security
License-File: LICENSE
Requires-Dist: colorama
Requires-Dist: flask
Requires-Dist: flask-httpauth
Requires-Dist: werkzeug
Requires-Dist: pyopenssl
Requires-Dist: qrcode
Requires-Dist: pillow
